LICENSE.md
MANIFEST.in
README.md
rule.py
setup.py
widget.py
xiangcheck.py
xiangcheck.egg-info/PKG-INFO
xiangcheck.egg-info/SOURCES.txt
xiangcheck.egg-info/dependency_links.txt
xiangcheck.egg-info/top_level.txt