Metadata-Version: 1.0
Name: xiangcheck
Version: 0.1.2
Summary: Validate move correctness for Xiangqi apps
Home-page: UNKNOWN
Author: Michael Marsh
Author-email: michael.marsh42@gmail.com
License: MIT
Platform: UNKNOWN
